lstar_lm/__init__.py
lstar_lm/dfa_lstar_learner.py
lstar_lm/dfa_sat_learner.py
lstar_lm/llm.py
lstar_lm/lstar_lm.py
lstar_lm-0.2.1.dist-info/LICENSE
lstar_lm-0.2.1.dist-info/METADATA
lstar_lm-0.2.1.dist-info/WHEEL
lstar_lm-0.2.1.dist-info/RECORD
