Metadata-Version: 2.1
Name: lstar_lm
Version: 0.2.1
Summary: Algorithm for learning DFA from demonstrations, examples, and language.
Author: Marcell Vazquez-Chanlatte
Author-email: mvc@linux.com
Requires-Python: >=3.10,<4.0
Classifier: Programming Language :: Python :: 3
Classifier: Programming Language :: Python :: 3.10
Classifier: Programming Language :: Python :: 3.11
Classifier: Programming Language :: Python :: 3.12
Requires-Dist: dfa-identify (>=3.11,<4.0)
Requires-Dist: httpx (>=0.26.0,<0.27.0)
Requires-Dist: lstar (>=1.0.1,<2.0.0)
